LICENSE.txt
MANIFEST.in
setup.py
IxNetRestApi/ClassInheritance.py
IxNetRestApi/IxNetRestApi.py
IxNetRestApi/IxNetRestApiClassicProtocol.py
IxNetRestApi/IxNetRestApiFileMgmt.py
IxNetRestApi/IxNetRestApiGlobals.py
IxNetRestApi/IxNetRestApiPacketCapture.py
IxNetRestApi/IxNetRestApiPortMgmt.py
IxNetRestApi/IxNetRestApiProtocol.py
IxNetRestApi/IxNetRestApiQuickTest.py
IxNetRestApi/IxNetRestApiStatistics.py
IxNetRestApi/IxNetRestApiTraffic.py
IxNetRestApi/__init__.py
IxNetRestApi.egg-info/PKG-INFO
IxNetRestApi.egg-info/SOURCES.txt
IxNetRestApi.egg-info/dependency_links.txt
IxNetRestApi.egg-info/requires.txt
IxNetRestApi.egg-info/top_level.txt
IxNetRestApi/SampleScripts/QuickTestNgpf_vm8.20.ixncfg
IxNetRestApi/SampleScripts/addPacketHeaderRawTraffic.py
IxNetRestApi/SampleScripts/bgp.json
IxNetRestApi/SampleScripts/bgpNgpf.py
IxNetRestApi/SampleScripts/bgpSimplified.json
IxNetRestApi/SampleScripts/bgpTestDUT.py
IxNetRestApi/SampleScripts/bgp_dut_8.50.ixncfg
IxNetRestApi/SampleScripts/bgp_eos.cfg
IxNetRestApi/SampleScripts/bgp_ngpf_8.30.ixncfg
IxNetRestApi/SampleScripts/bierIsisNgpf.py
IxNetRestApi/SampleScripts/bulkConfiguration.py
IxNetRestApi/SampleScripts/dhcpClientServerV4.py
IxNetRestApi/SampleScripts/egressTrackingNgpf.py
IxNetRestApi/SampleScripts/isisNgpf.py
IxNetRestApi/SampleScripts/ixVmChassisBuilderRestApi.py
IxNetRestApi/SampleScripts/ixvmParams.py
IxNetRestApi/SampleScripts/jsonConfigImportExportSamples.py
IxNetRestApi/SampleScripts/l2l3Ngpf.py
IxNetRestApi/SampleScripts/lacpOspfNgpf.py
IxNetRestApi/SampleScripts/loadConfigFile.py
IxNetRestApi/SampleScripts/loadJsonConfigFile.py
IxNetRestApi/SampleScripts/loadQuickTest.py
IxNetRestApi/SampleScripts/mplsNgpf.py
IxNetRestApi/SampleScripts/mplsRawTraffic.py
IxNetRestApi/SampleScripts/ospfNgpf.py
IxNetRestApi/SampleScripts/packetCapture.py
IxNetRestApi/SampleScripts/resume.py
IxNetRestApi/SampleScripts/vxlanNgpf.py
IxNetRestApi/SampleScripts/LoadConfigWithInputFile/__init__.py
IxNetRestApi/SampleScripts/LoadConfigWithInputFile/bgpParams.py
IxNetRestApi/SampleScripts/LoadConfigWithInputFile/configIxNetwork.py
IxNetRestApi/SampleScripts/LoadConfigWithInputFile/l2l3Params.py
