Metadata-Version: 1.2
Name: IxNetRestApi
Version: 2018.1128.1
Summary: API modules and sample scripts to accelerate your script development
Home-page: https://github.com/openixia/ixnetwork
Author: Hubert Gee
Author-email: hubert.gee@keysight.com
Maintainer: Hubert Gee
License: MIT
Platform: UNKNOWN
